pythonGateway/Api.py
pythonGateway/__init__.py
pythonGateway-1.1.dist-info/LICENSE
pythonGateway-1.1.dist-info/METADATA
pythonGateway-1.1.dist-info/WHEEL
pythonGateway-1.1.dist-info/top_level.txt
pythonGateway-1.1.dist-info/RECORD
