Metadata-Version: 2.1
Name: pythonGateway
Version: 1.1
Summary: Python wrapper for Bitocredit API
Home-page: https://github.com/bitocredit/python-gateway
Author: Reza Motahary
Author-email: reza.rz00980pp@gmail.com
License: MIT
Classifier: Programming Language :: Python :: 3
Classifier: Programming Language :: Python :: 2
Classifier: License :: OSI Approved :: MIT License
Classifier: Operating System :: OS Independent
License-File: LICENSE
Requires-Dist: requests
